Metadata-Version: 1.1
Name: subs
Version: 0.0.0a0
Summary: tmp
Home-page: https://github.com/feluxe/subs
Author: Felix Meyer-Wolters
Author-email: felix@meyerwolters.de
License: unlicensed
Download-URL: https://github.com/feluxe/subs/tarball/0.0.0-alpha.0
Keywords: tmp
Platform: 
